fin_crawler/__init__.py
fin_crawler/crawler.py
fin_crawler/fetcher.py
fin_crawler/parameter.py
fin_crawler/plugins/__init__.py
fin_crawler/plugins/tw_col_names.py
fin_crawler/plugins/tw_institutional_investors_daily.py
fin_crawler/plugins/tw_stock_info.py
fin_crawler/plugins/tw_stock_price.py
fin_crawler/plugins/tw_stock_price_daily.py
fin_crawler/plugins/utils.py
tests/__init__.py
tests/test_crawler.py
tests/test_fetcher.py
tests/test_plugins_utils.py
tests/test_tw_institutional_investors_daily.py
tests/test_tw_institutional_investors_daily_real.py
tests/test_tw_stock_info.py
tests/test_tw_stock_info_real.py
tests/test_tw_stock_price.py
tests/test_tw_stock_price_daily.py
tests/test_tw_stock_price_daily_real.py
tests/test_tw_stock_price_real.py
fin_crawler-0.1.2.dist-info/LICENSE
fin_crawler-0.1.2.dist-info/METADATA
fin_crawler-0.1.2.dist-info/WHEEL
fin_crawler-0.1.2.dist-info/top_level.txt
fin_crawler-0.1.2.dist-info/RECORD
