Metadata-Version: 2.1
Name: fin-crawler
Version: 0.1.2
Summary: Financial data crawler
Home-page: https://github.com/cwhuang119/fin_crawler
Author: Tom Huang
Author-email: cwhuang119@gmail.com
Project-URL: Bug Tracker, https://github.com/cwhuang119/fin_crawler/issues
Classifier: Programming Language :: Python :: 3
Classifier: License :: OSI Approved :: Apache Software License
Classifier: Operating System :: OS Independent
Requires-Python: >=3.6
License-File: LICENSE
Requires-Dist: requests
